{"airflow": [1, "/categories/airflow/"], "python": [4, "/categories/python/"], "luigi": [1, "/categories/luigi/"], "twitter": [1, "/categories/twitter/"], "Raspbian": [1, "/categories/raspbian/"], "pycon": [1, "/categories/pycon/"], "TAS": [1, "/categories/tas/"], "azkaban": [4, "/categories/azkaban/"], "GitBucket": [1, "/categories/gitbucket/"], "Linux": [1, "/categories/linux/"], "GitHub": [1, "/categories/github/"], "ffmpeg": [1, "/categories/ffmpeg/"], "hugo": [2, "/categories/hugo/"], "chinachu": [6, "/categories/chinachu/"], "ttytter": [2, "/categories/ttytter/"], "ubuntu": [8, "/categories/ubuntu/"], "nikola": [1, "/categories/nikola/"], "gitbook pdf": [1, "/categories/gitbook-pdf/"], "B-CAS": [1, "/categories/b-cas/"], "Jenkins": [1, "/categories/jenkins/"], "rundeck": [1, "/categories/rundeck/"], "nicovideo": [1, "/categories/nicovideo/"], "comskip": [1, "/categories/comskip/"], "WAQWAQ": [2, "/categories/waqwaq/"]}